{"is_source_file": true, "format": "bash", "description": "A shell script that detects and creates backups of different types of databases (SQLite, PostgreSQL, MySQL, MongoDB) based on their presence and status on the system.", "external_files": ["/usr/lib/postgresql/", "/var/run/mysqld/mysqld.sock"], "external_methods": ["ls", "sudo -u postgres pg_isready", "mysqladmin", "mysql", "mysqldump", "mongosh", "mongodump"], "published": [], "classes": [], "methods": [], "calls": ["ls", "sudo -u postgres pg_isready", "mysqladmin ping", "mysql -h localhost -P ${DB_PORT} -u ${DB_USER} -p${DB_PASSWORD}", "mysqldump", "sudo mysql --socket=/var/run/mysqld/mysqld.sock -u root -p${DB_PASSWORD} -e \"SELECT 1\"", "mongosh --port ${DB_PORT} --eval \"db.adminCommand('ping')\"", "mongodump --port ${DB_PORT} --db ${DB_NAME} --archive=database_backup.archive --quiet"], "search-terms": ["backup shell script", "detect database type", "PostgreSQL backup", "MySQL backup", "SQLite backup", "MongoDB backup", "database detection", "backup detection script"], "state": 2, "file_id": 6, "knowledge_revision": 14, "git_revision": "f7d763852994326f60a66997875767ca9f013444", "hash": "7af9aa35fa4940f934d83f6e2621b732", "format-version": 4, "code-base-name": "database_postgresql", "filename": "database_postgresql/backup_db.sh", "revision_history": [{"14": "f7d763852994326f60a66997875767ca9f013444"}]}